pypika_tortoise/dialects/duckdb.py
tortoise/patch.py
tortoise/backends/duckdb/__init__.py
tortoise/backends/duckdb/client.py
tortoise/backends/duckdb/executor.py
tortoise/backends/duckdb/schema_generator.py
tortoise/contrib/duckdb/__init__.py
tortoise/contrib/duckdb/functions.py
tortoise/contrib/duckdb/regex.py
tortoise_orm_extra_duckdb-2025.9.15.dist-info/licenses/LICENSE
tortoise_orm_extra_duckdb-2025.9.15.dist-info/METADATA
tortoise_orm_extra_duckdb-2025.9.15.dist-info/WHEEL
tortoise_orm_extra_duckdb-2025.9.15.dist-info/top_level.txt
tortoise_orm_extra_duckdb-2025.9.15.dist-info/RECORD
