Metadata-Version: 2.4
Name: tortoise-orm-extra-duckdb
Version: 2025.9.15
Summary: Tortoise ORM backend for DuckDB
Author-email: fairydream <cn.fairydream@outlook.com>
License-Expression: MIT
Project-URL: Homepage, https://github.com/cnfairydream/tortoise-orm-extra-duckdb
Project-URL: Repository, https://github.com/cnfairydream/tortoise-orm-extra-duckdb
Requires-Python: <4.0,>=3.11
License-File: LICENSE
Requires-Dist: aioduck
Requires-Dist: tortoise-orm
Dynamic: license-file
